setup.py
xzc/__init__.py
xzc.egg-info/PKG-INFO
xzc.egg-info/SOURCES.txt
xzc.egg-info/dependency_links.txt
xzc.egg-info/top_level.txt