Metadata-Version: 2.1
Name: xzc
Version: 1.0
Summary: a small pkg demos for everyone of students
Home-page: UNKNOWN
License: UNKNOWN
Platform: UNKNOWN
